LICENSE.txt
MANIFEST.in
readme.md
setup.cfg
setup.py
pybeauty/__init__.py
pybeauty/pybeauty.py
pybeauty.egg-info/PKG-INFO
pybeauty.egg-info/SOURCES.txt
pybeauty.egg-info/dependency_links.txt
pybeauty.egg-info/top_level.txt