Metadata-Version: 2.1
Name: pybeauty
Version: 1.0
Summary: Python module for beautifully varying RGB colour sets which can be used for setting colours anywhere!
Home-page: https://github.com/AbhayTr/PyBeauty
Author: Abhay Tripathi
Author-email: abhay.triipathi@gmail.com
License: MIT
Download-URL: https://github.com/AbhayTr/PyBeauty/archive/v1.0.tar.gz
Keywords: Beauty,RGB,PyBeauty,Stunning backgrounds,colours,varying colours
Platform: UNKNOWN
Classifier: Development Status :: 5 - Production/Stable
Classifier: Intended Audience :: Developers
Classifier: Topic :: Software Development :: Build Tools
Classifier: License :: OSI Approved :: MIT License
Classifier: Programming Language :: Python :: 2
Classifier: Programming Language :: Python :: 3
Classifier: Programming Language :: Python :: 3.4
Classifier: Programming Language :: Python :: 3.5
Classifier: Programming Language :: Python :: 3.6
